freedata_server/__init__.py
freedata_server/api_validations.py
freedata_server/arq_data_type_handler.py
freedata_server/arq_session.py
freedata_server/arq_session_irs.py
freedata_server/arq_session_iss.py
freedata_server/audio.py
freedata_server/codec2.py
freedata_server/command.py
freedata_server/command_arq_raw.py
freedata_server/command_beacon.py
freedata_server/command_cq.py
freedata_server/command_feq.py
freedata_server/command_message_send.py
freedata_server/command_p2p_connection.py
freedata_server/command_ping.py
freedata_server/command_qrv.py
freedata_server/command_test.py
freedata_server/config.py
freedata_server/cw.py
freedata_server/data_frame_factory.py
freedata_server/demodulator.py
freedata_server/event_manager.py
freedata_server/exceptions.py
freedata_server/explorer.py
freedata_server/frame_dispatcher.py
freedata_server/frame_handler.py
freedata_server/frame_handler_arq_session.py
freedata_server/frame_handler_beacon.py
freedata_server/frame_handler_cq.py
freedata_server/frame_handler_p2p_connection.py
freedata_server/frame_handler_ping.py
freedata_server/helpers.py
freedata_server/log_handler.py
freedata_server/maidenhead.py
freedata_server/mesh.py
freedata_server/message_p2p.py
freedata_server/message_system_db_attachments.py
freedata_server/message_system_db_beacon.py
freedata_server/message_system_db_manager.py
freedata_server/message_system_db_messages.py
freedata_server/message_system_db_model.py
freedata_server/modem.py
freedata_server/modem_frametypes.py
freedata_server/modulator.py
freedata_server/p2p_connection.py
freedata_server/queues.py
freedata_server/radio_manager.py
freedata_server/rigctld.py
freedata_server/rigdummy.py
freedata_server/schedule_manager.py
freedata_server/selftest.py
freedata_server/serial_ports.py
freedata_server/server.py
freedata_server/service_manager.py
freedata_server/socket_interface.py
freedata_server/socket_interface_commands.py
freedata_server/state_manager.py
freedata_server/stats.py
freedata_server-0.15.4.dist-info/LICENSE
freedata_server-0.15.4.dist-info/METADATA
freedata_server-0.15.4.dist-info/WHEEL
freedata_server-0.15.4.dist-info/entry_points.txt
freedata_server-0.15.4.dist-info/top_level.txt
freedata_server-0.15.4.dist-info/RECORD
