Metadata-Version: 2.1
Name: freedata-server
Version: 0.15.4
Summary: A free, open-source, multi-platform application for sending files and messages, using the codec2 HF modems.
Home-page: https://freedata.app
Author: DJ2LS
Author-email: dj2ls@proton.me
License: GPL3.0
Requires-Python: >=3.9
License-File: LICENSE
Requires-Dist: crcengine
Requires-Dist: numpy
Requires-Dist: psutil
Requires-Dist: PyAudio
Requires-Dist: pyserial
Requires-Dist: sounddevice
Requires-Dist: structlog
Requires-Dist: requests
Requires-Dist: chardet
Requires-Dist: colorama
Requires-Dist: ordered-set
Requires-Dist: nuitka
Requires-Dist: pyinstaller
Requires-Dist: websocket-client
Requires-Dist: flask
Requires-Dist: flask-sock
Requires-Dist: flask-cors
Requires-Dist: autopep8
Requires-Dist: black
Requires-Dist: isort
Requires-Dist: pycodestyle
Requires-Dist: pytest
Requires-Dist: pytest-cov
Requires-Dist: pytest-cover
Requires-Dist: pytest-coverage
Requires-Dist: pytest-rerunfailures
Requires-Dist: pick
Requires-Dist: sqlalchemy
